[{"model": "api.categorieactif", "pk": "076258c5-3945-4329-b75e-c75f26cbf137", "fields": {"created_at": "2025-12-03T21:33:21.646Z", "updated_at": "2025-12-03T21:33:21.646Z", "nom": "Données", "description": "Bases de données et systèmes de stockage de données", "code": "DATA"}}, {"model": "api.categorieactif", "pk": "299ecae7-e939-4d4d-959c-5968b9aafce7", "fields": {"created_at": "2025-12-05T21:38:49.463Z", "updated_at": "2025-12-05T21:39:30.329Z", "nom": "catego", "description": "txytufjyk", "code": "CAT"}}, {"model": "api.categorieactif", "pk": "423c84a0-1546-47f2-986d-0faf4e594ce6", "fields": {"created_at": "2025-12-03T21:33:21.642Z", "updated_at": "2025-12-03T21:33:21.642Z", "nom": "Général", "description": "Catégorie générale pour les types non classifiés", "code": "GENERAL"}}, {"model": "api.categorieactif", "pk": "5bab3b4f-3524-4df6-a521-3bb0b8e688e2", "fields": {"created_at": "2025-12-03T21:33:21.645Z", "updated_at": "2025-12-03T21:33:21.645Z", "nom": "Applications", "description": "Applications et logiciels (web, mobile, desktop)", "code": "APP"}}, {"model": "api.categorieactif", "pk": "64619b7a-95fc-4960-aca1-758fa8a73eb1", "fields": {"created_at": "2025-12-03T21:33:21.643Z", "updated_at": "2025-12-03T21:33:21.643Z", "nom": "Infrastructure", "description": "Infrastructure matérielle et réseau (serveurs, équipements réseau, stockage)", "code": "INFRA"}}, {"model": "api.categorieactif", "pk": "ad58b8d9-e209-48d5-8872-5b877c492189", "fields": {"created_at": "2025-12-03T21:33:21.647Z", "updated_at": "2025-12-03T21:33:21.647Z", "nom": "Services", "description": "Services métier et services cloud", "code": "SERVICE"}}, {"model": "api.categorieactif", "pk": "b97fd60e-af07-4648-ac32-534edd7dca06", "fields": {"created_at": "2025-12-03T21:33:21.648Z", "updated_at": "2025-12-03T21:33:21.648Z", "nom": "Réseau", "description": "Équipements et services réseau", "code": "RESEAU"}}, {"model": "api.typeactif", "pk": "b7b06001-20a2-457d-8eee-22dfbcba0dfb", "fields": {"created_at": "2025-12-05T21:49:23.800Z", "updated_at": "2025-12-05T21:49:23.800Z", "categorie": "076258c5-3945-4329-b75e-c75f26cbf137", "nom": "Type1", "description": "fgdfhn", "code": "TTY"}}, {"model": "api.typeactif", "pk": "e5c1c845-62ae-490c-bc19-b056fd80c832", "fields": {"created_at": "2025-12-03T20:12:48.606Z", "updated_at": "2025-12-05T21:50:32.214Z", "categorie": "b97fd60e-af07-4648-ac32-534edd7dca06", "nom": "Type one", "description": "", "code": "TOOOO"}}, {"model": "api.architecture", "pk": "e20bdb96-fd84-4c81-97c8-cd584500d616", "fields": {"created_at": "2025-12-03T20:11:04.828Z", "updated_at": "2025-12-03T20:11:04.828Z", "nom": "Système d'information du groupe Eudoxie Holding", "description": "gxhfgcjhv,;", "risque_tolere": "10000.00"}}, {"model": "api.actif", "pk": "9e680038-cec1-4ff5-8824-cd6a9568229a", "fields": {"created_at": "2025-12-03T20:13:12.688Z", "updated_at": "2025-12-03T20:13:12.688Z", "nom": "Base de données Sql Serveur", "description": "dgxhcgjvb,;", "cout": "120.00", "type_actif": "e5c1c845-62ae-490c-bc19-b056fd80c832", "architecture": "e20bdb96-fd84-4c81-97c8-cd584500d616", "proprietaire": null, "criticite": "MOYEN"}}, {"model": "api.attributsecurite", "pk": "daa358c3-a0df-4344-bc40-28579b326aff", "fields": {"created_at": "2025-12-03T20:13:31.959Z", "updated_at": "2025-12-03T20:13:31.959Z", "actif": "9e680038-cec1-4ff5-8824-cd6a9568229a", "type_attribut": "CONFIDENTIALITE", "cout_compromission": "20.00", "priorite": "P2"}}, {"model": "api.menace", "pk": "ebd03d48-3051-458e-ba1d-2188fb7b62c0", "fields": {"created_at": "2025-12-03T20:13:55.119Z", "updated_at": "2025-12-03T20:13:55.119Z", "nom": "Ransomware", "description": "gfxhcv;j", "type_menace": "Denial of Service (DoS)", "severite": "MOYEN", "attribut_securite_principal": "daa358c3-a0df-4344-bc40-28579b326aff"}}, {"model": "api.attributmenace", "pk": "409b2222-4d90-4493-b739-cb563b641c2b", "fields": {"created_at": "2025-12-03T20:13:55.120Z", "updated_at": "2025-12-03T20:13:55.120Z", "attribut_securite": "daa358c3-a0df-4344-bc40-28579b326aff", "menace": "ebd03d48-3051-458e-ba1d-2188fb7b62c0", "probabilite": "70.00", "impact": "100.00", "cout_impact": "20.00"}}